pyspark_dataframe_extras/__init__.py
pyspark_dataframe_extras/common/__init__.py
pyspark_dataframe_extras/common/dataframe_ext.py
pyspark_dataframe_extras-0.0.1.dist-info/LICENSE
pyspark_dataframe_extras-0.0.1.dist-info/WHEEL
pyspark_dataframe_extras-0.0.1.dist-info/METADATA
pyspark_dataframe_extras-0.0.1.dist-info/RECORD
